waxfetcher/__init__.py
waxfetcher/waxfetcher.py
waxfetcher-0.1.4.dist-info/METADATA
waxfetcher-0.1.4.dist-info/WHEEL
waxfetcher-0.1.4.dist-info/top_level.txt
waxfetcher-0.1.4.dist-info/RECORD
